gitlab_http_logger/__init__.py
gitlab_http_logger/handler.py
GitlabHttpLogger-0.0.1.dist-info/LICENSE
GitlabHttpLogger-0.0.1.dist-info/METADATA
GitlabHttpLogger-0.0.1.dist-info/WHEEL
GitlabHttpLogger-0.0.1.dist-info/top_level.txt
GitlabHttpLogger-0.0.1.dist-info/RECORD
