Metadata-Version: 2.1
Name: GitlabHttpLogger
Version: 0.0.1
Summary: A simple logging handler to publish logs to the GitLab HTTP Alert system.
Author-email: Lukáš Hejcman <lukas.hejcman@outlook.com>
License: This is free and unencumbered software released into the public domain.        
Classifier: Programming Language :: Python :: 3
Classifier: License :: OSI Approved :: The Unlicense (Unlicense)
Classifier: Operating System :: OS Independent
Classifier: Development Status :: 3 - Alpha
Classifier: Natural Language :: English
Requires-Python: >=3.5
License-File: LICENSE
Requires-Dist: requests
